odoo/addons/sale_timesheet_order_line_sync/README.rst
odoo/addons/sale_timesheet_order_line_sync/__init__.py
odoo/addons/sale_timesheet_order_line_sync/__manifest__.py
odoo/addons/sale_timesheet_order_line_sync/i18n/es.po
odoo/addons/sale_timesheet_order_line_sync/i18n/sale_timesheet_order_line_sync.pot
odoo/addons/sale_timesheet_order_line_sync/models/__init__.py
odoo/addons/sale_timesheet_order_line_sync/models/project_task.py
odoo/addons/sale_timesheet_order_line_sync/readme/CONTRIBUTORS.rst
odoo/addons/sale_timesheet_order_line_sync/readme/DESCRIPTION.rst
odoo/addons/sale_timesheet_order_line_sync/readme/USAGE.rst
odoo/addons/sale_timesheet_order_line_sync/static/description/icon.png
odoo/addons/sale_timesheet_order_line_sync/static/description/index.html
odoo/addons/sale_timesheet_order_line_sync/tests/__init__.py
odoo/addons/sale_timesheet_order_line_sync/tests/test_sale_timesheet_order_line_sync.py
odoo12_addon_sale_timesheet_order_line_sync-12.0.1.0.1.dist-info/METADATA
odoo12_addon_sale_timesheet_order_line_sync-12.0.1.0.1.dist-info/WHEEL
odoo12_addon_sale_timesheet_order_line_sync-12.0.1.0.1.dist-info/top_level.txt
odoo12_addon_sale_timesheet_order_line_sync-12.0.1.0.1.dist-info/RECORD
